{
	"song": {
		"sectionLengths": [],
		"player1": "bf",
		"player2": "vaporeon",
		"notes": [
			{
				"sectionNotes": [
					[
						0,
						-1,
						"Default CamHUD Zoom",
						"-1",
						"0.0001"
					]
				],
				"lengthInSteps": 16,
				"typeOfSection": 0,
				"mustHitSection": true
			},
			{
				"sectionNotes": [
					[
						3500,
						5,
						0
					]
				],
				"lengthInSteps": 16,
				"typeOfSection": 0,
				"mustHitSection": true
			},
			{
				"sectionNotes": [],
				"lengthInSteps": 16,
				"typeOfSection": 0,
				"mustHitSection": true
			},
			{
				"sectionNotes": [],
				"lengthInSteps": 16,
				"typeOfSection": 0,
				"mustHitSection": true
			},
			{
				"sectionNotes": [
					[
						8000,
						-1,
						"Default Camera Zoom",
						"1.25",
						"2"
					]
				],
				"lengthInSteps": 16,
				"typeOfSection": 0,
				"mustHitSection": false
			},
			{
				"sectionNotes": [
					[
						11500,
						1,
						0
					]
				],
				"lengthInSteps": 16,
				"typeOfSection": 0,
				"mustHitSection": false
			},
			{
				"sectionNotes": [
					[
						12000,
						-1,
						"Default Camera Zoom",
						"1",
						"0.5"
					]
				],
				"lengthInSteps": 16,
				"typeOfSection": 0,
				"mustHitSection": true
			},
			{
				"sectionNotes": [],
				"lengthInSteps": 16,
				"typeOfSection": 0,
				"mustHitSection": true
			},
			{
				"sectionNotes": [
					[
						16000,
						1,
						0
					],
					[
						16500,
						1,
						0
					],
					[
						17000,
						1,
						0
					],
					[
						17500,
						2,
						0
					],
					[
						17750,
						2,
						0
					],
					[
						16250,
						3,
						0
					],
					[
						16000,
						-1,
						"Default CamHUD Zoom",
						"1.15",
						"0.0001"
					],
					[
						16025,
						-1,
						"Default CamHUD Zoom",
						"1",
						"2"
					]
				],
				"lengthInSteps": 16,
				"typeOfSection": 0,
				"mustHitSection": false
			},
			{
				"sectionNotes": [
					[
						18000,
						1,
						0
					],
					[
						18750,
						1,
						0
					],
					[
						19125,
						3,
						0
					],
					[
						19250,
						1,
						0
					],
					[
						19500,
						1,
						0
					],
					[
						19750,
						2,
						0
					],
					[
						18375,
						2,
						0
					]
				],
				"lengthInSteps": 16,
				"typeOfSection": 0,
				"mustHitSection": false
			},
			{
				"sectionNotes": [
					[
						20000,
						1,
						0
					],
					[
						20250,
						0,
						0
					],
					[
						20375,
						2,
						0
					],
					[
						20500,
						3,
						0
					],
					[
						20750,
						2,
						0
					],
					[
						21000,
						1,
						0
					],
					[
						21500,
						3,
						0
					],
					[
						21750,
						2,
						0
					]
				],
				"lengthInSteps": 16,
				"typeOfSection": 0,
				"mustHitSection": false
			},
			{
				"sectionNotes": [
					[
						22000,
						1,
						0
					],
					[
						22250,
						1,
						0
					],
					[
						22375,
						0,
						0
					],
					[
						22500,
						1,
						0
					],
					[
						22750,
						3,
						0
					],
					[
						22875,
						1,
						0
					],
					[
						23125,
						2,
						0
					],
					[
						23750,
						2,
						0
					],
					[
						23250,
						1,
						0
					],
					[
						23375,
						0,
						0
					],
					[
						23500,
						1,
						0
					]
				],
				"lengthInSteps": 16,
				"typeOfSection": 0,
				"mustHitSection": false
			},
			{
				"sectionNotes": [
					[
						24000,
						1,
						0
					],
					[
						24500,
						1,
						0
					],
					[
						25000,
						1,
						0
					],
					[
						25500,
						2,
						0
					],
					[
						25750,
						2,
						0
					],
					[
						24250,
						3,
						0
					]
				],
				"lengthInSteps": 16,
				"typeOfSection": 0,
				"mustHitSection": true
			},
			{
				"sectionNotes": [
					[
						26000,
						1,
						0
					],
					[
						26750,
						1,
						0
					],
					[
						27125,
						3,
						0
					],
					[
						27250,
						1,
						0
					],
					[
						27500,
						1,
						0
					],
					[
						27750,
						2,
						0
					],
					[
						26375,
						2,
						0
					]
				],
				"lengthInSteps": 16,
				"typeOfSection": 0,
				"mustHitSection": true
			},
			{
				"sectionNotes": [
					[
						28000,
						1,
						0
					],
					[
						28250,
						0,
						0
					],
					[
						28375,
						2,
						0
					],
					[
						28500,
						3,
						0
					],
					[
						28750,
						2,
						0
					],
					[
						29000,
						1,
						0
					],
					[
						29500,
						3,
						0
					],
					[
						29750,
						2,
						0
					]
				],
				"lengthInSteps": 16,
				"typeOfSection": 0,
				"mustHitSection": true
			},
			{
				"sectionNotes": [
					[
						30000,
						1,
						0
					],
					[
						30250,
						1,
						0
					],
					[
						30375,
						0,
						0
					],
					[
						30500,
						1,
						0
					],
					[
						30750,
						3,
						0
					],
					[
						30875,
						1,
						0
					],
					[
						31125,
						2,
						0
					],
					[
						31750,
						2,
						0
					],
					[
						31250,
						1,
						0
					],
					[
						31375,
						0,
						0
					],
					[
						31500,
						1,
						0
					]
				],
				"lengthInSteps": 16,
				"typeOfSection": 0,
				"mustHitSection": true
			},
			{
				"sectionNotes": [
					[
						32000,
						1,
						125
					],
					[
						32500,
						2,
						0
					],
					[
						32750,
						0,
						0
					],
					[
						33000,
						2,
						125
					],
					[
						33375,
						1,
						0
					],
					[
						33750,
						2,
						0
					]
				],
				"lengthInSteps": 16,
				"typeOfSection": 0,
				"mustHitSection": false
			},
			{
				"sectionNotes": [
					[
						34000,
						0,
						0
					],
					[
						34125,
						2,
						0
					],
					[
						34250,
						3,
						0
					],
					[
						34500,
						0,
						0
					],
					[
						35125,
						0,
						0
					],
					[
						35250,
						1,
						0
					],
					[
						35750,
						1,
						0
					],
					[
						35375,
						0,
						62.5
					],
					[
						34750,
						1,
						0
					],
					[
						35000,
						3,
						0
					]
				],
				"lengthInSteps": 16,
				"typeOfSection": 0,
				"mustHitSection": false
			},
			{
				"sectionNotes": [
					[
						36000,
						1,
						125
					],
					[
						36500,
						2,
						0
					],
					[
						36750,
						0,
						0
					],
					[
						37000,
						2,
						125
					],
					[
						37375,
						1,
						0
					],
					[
						37750,
						2,
						0
					],
					[
						36000,
						6,
						250
					]
				],
				"lengthInSteps": 16,
				"typeOfSection": 0,
				"mustHitSection": true
			},
			{
				"sectionNotes": [
					[
						38000,
						0,
						0
					],
					[
						38125,
						2,
						0
					],
					[
						38250,
						3,
						0
					],
					[
						38500,
						0,
						0
					],
					[
						39000,
						2,
						0
					],
					[
						39125,
						0,
						0
					],
					[
						39250,
						1,
						0
					],
					[
						39375,
						0,
						62.5
					],
					[
						38750,
						3,
						0
					],
					[
						39750,
						3,
						0
					]
				],
				"lengthInSteps": 16,
				"typeOfSection": 0,
				"mustHitSection": true
			},
			{
				"sectionNotes": [
					[
						40000,
						1,
						125
					],
					[
						40500,
						2,
						0
					],
					[
						40750,
						0,
						0
					],
					[
						41000,
						2,
						125
					],
					[
						41375,
						1,
						0
					],
					[
						41750,
						2,
						0
					],
					[
						40000,
						6,
						250
					]
				],
				"lengthInSteps": 16,
				"typeOfSection": 0,
				"mustHitSection": false
			},
			{
				"sectionNotes": [
					[
						42000,
						0,
						0
					],
					[
						42125,
						2,
						0
					],
					[
						42250,
						3,
						0
					],
					[
						42500,
						0,
						0
					],
					[
						43000,
						0,
						0
					],
					[
						43125,
						2,
						0
					],
					[
						43250,
						3,
						0
					],
					[
						43500,
						0,
						0
					],
					[
						42750,
						1,
						0
					],
					[
						43750,
						1,
						0
					]
				],
				"lengthInSteps": 16,
				"typeOfSection": 0,
				"mustHitSection": false
			},
			{
				"sectionNotes": [
					[
						44000,
						1,
						125
					],
					[
						44500,
						2,
						0
					],
					[
						44750,
						0,
						0
					],
					[
						45000,
						2,
						125
					],
					[
						45375,
						1,
						0
					],
					[
						45750,
						2,
						0
					],
					[
						44000,
						4,
						250
					]
				],
				"lengthInSteps": 16,
				"typeOfSection": 0,
				"mustHitSection": true
			},
			{
				"sectionNotes": [
					[
						46000,
						0,
						0
					],
					[
						46125,
						2,
						0
					],
					[
						46250,
						3,
						0
					],
					[
						46500,
						0,
						0
					],
					[
						46750,
						3,
						0
					],
					[
						47750,
						3,
						0
					],
					[
						47000,
						0,
						0
					],
					[
						47125,
						2,
						0
					],
					[
						47250,
						3,
						0
					],
					[
						47500,
						0,
						0
					]
				],
				"lengthInSteps": 16,
				"typeOfSection": 0,
				"mustHitSection": true
			},
			{
				"sectionNotes": [
					[
						48000,
						1,
						687.5
					],
					[
						49000,
						2,
						687.5
					],
					[
						48000,
						4,
						250
					],
					[
						48000,
						-1,
						"Set Camera Zoom",
						"2",
						"2"
					]
				],
				"lengthInSteps": 16,
				"typeOfSection": 0,
				"mustHitSection": false
			},
			{
				"sectionNotes": [
					[
						51000,
						1,
						687.5
					]
				],
				"lengthInSteps": 16,
				"typeOfSection": 0,
				"mustHitSection": false
			},
			{
				"sectionNotes": [
					[
						52000,
						0,
						812.5
					],
					[
						53500,
						1,
						187.5
					]
				],
				"lengthInSteps": 16,
				"typeOfSection": 0,
				"mustHitSection": false
			},
			{
				"typeOfSection": 0,
				"sectionNotes": [
					[
						54000,
						0,
						687.5
					],
					[
						55000,
						2,
						687.5
					]
				],
				"lengthInSteps": 16,
				"bpm": 100,
				"changeBPM": false,
				"mustHitSection": false
			},
			{
				"typeOfSection": 0,
				"sectionNotes": [
					[
						56000,
						1,
						687.5
					],
					[
						57000,
						2,
						687.5
					],
					[
						56000,
						5,
						687.5
					],
					[
						57000,
						6,
						687.5
					]
				],
				"lengthInSteps": 16,
				"altAnim": false,
				"bpm": 100,
				"changeBPM": false,
				"mustHitSection": true
			},
			{
				"typeOfSection": 0,
				"sectionNotes": [
					[
						59000,
						1,
						687.5
					],
					[
						59000,
						5,
						687.5
					]
				],
				"lengthInSteps": 16,
				"altAnim": false,
				"bpm": 100,
				"changeBPM": false,
				"mustHitSection": true
			},
			{
				"typeOfSection": 0,
				"sectionNotes": [
					[
						60000,
						4,
						812.5
					],
					[
						61500,
						5,
						187.5
					],
					[
						61500,
						1,
						187.5
					],
					[
						60000,
						0,
						812.5
					]
				],
				"lengthInSteps": 16,
				"altAnim": false,
				"bpm": 120,
				"changeBPM": false,
				"mustHitSection": true
			},
			{
				"typeOfSection": 0,
				"sectionNotes": [
					[
						62000,
						0,
						687.5
					],
					[
						63000,
						2,
						687.5
					],
					[
						62000,
						4,
						687.5
					],
					[
						63000,
						6,
						687.5
					]
				],
				"lengthInSteps": 16,
				"altAnim": false,
				"bpm": 120,
				"changeBPM": false,
				"mustHitSection": true
			},
			{
				"typeOfSection": 0,
				"sectionNotes": [
					[
						64000,
						1,
						0
					],
					[
						64500,
						1,
						0
					],
					[
						65000,
						1,
						0
					],
					[
						65500,
						2,
						0
					],
					[
						65750,
						2,
						0
					],
					[
						64250,
						3,
						0
					],
					[
						64000,
						-1,
						"Set Camera Zoom",
						"1",
						"0.5"
					]
				],
				"lengthInSteps": 16,
				"altAnim": false,
				"bpm": 120,
				"changeBPM": false,
				"mustHitSection": false
			},
			{
				"typeOfSection": 0,
				"sectionNotes": [
					[
						66000,
						1,
						0
					],
					[
						66750,
						1,
						0
					],
					[
						67125,
						3,
						0
					],
					[
						67250,
						1,
						0
					],
					[
						67500,
						1,
						0
					],
					[
						67750,
						2,
						0
					],
					[
						66375,
						2,
						0
					]
				],
				"lengthInSteps": 16,
				"altAnim": false,
				"bpm": 120,
				"changeBPM": false,
				"mustHitSection": false
			},
			{
				"typeOfSection": 0,
				"sectionNotes": [
					[
						68000,
						1,
						0
					],
					[
						68250,
						0,
						0
					],
					[
						68375,
						2,
						0
					],
					[
						68500,
						3,
						0
					],
					[
						68750,
						2,
						0
					],
					[
						69000,
						1,
						0
					],
					[
						69500,
						3,
						0
					],
					[
						69750,
						2,
						0
					]
				],
				"lengthInSteps": 16,
				"altAnim": false,
				"bpm": 120,
				"changeBPM": false,
				"mustHitSection": false
			},
			{
				"typeOfSection": 0,
				"sectionNotes": [
					[
						70000,
						1,
						0
					],
					[
						70250,
						1,
						0
					],
					[
						70375,
						0,
						0
					],
					[
						70500,
						1,
						0
					],
					[
						70750,
						3,
						0
					],
					[
						70875,
						1,
						0
					],
					[
						71125,
						2,
						0
					],
					[
						71750,
						2,
						0
					],
					[
						71250,
						1,
						0
					],
					[
						71375,
						0,
						0
					],
					[
						71500,
						1,
						0
					]
				],
				"lengthInSteps": 16,
				"altAnim": false,
				"bpm": 120,
				"changeBPM": false,
				"mustHitSection": false
			},
			{
				"typeOfSection": 0,
				"sectionNotes": [
					[
						72000,
						1,
						0
					],
					[
						72500,
						1,
						0
					],
					[
						73000,
						1,
						0
					],
					[
						73500,
						2,
						0
					],
					[
						73750,
						2,
						0
					],
					[
						72250,
						3,
						0
					]
				],
				"lengthInSteps": 16,
				"altAnim": false,
				"bpm": 120,
				"changeBPM": false,
				"mustHitSection": true
			},
			{
				"typeOfSection": 0,
				"sectionNotes": [
					[
						74000,
						1,
						0
					],
					[
						74750,
						1,
						0
					],
					[
						75125,
						3,
						0
					],
					[
						75250,
						1,
						0
					],
					[
						75500,
						1,
						0
					],
					[
						75750,
						2,
						0
					],
					[
						74375,
						2,
						0
					]
				],
				"lengthInSteps": 16,
				"altAnim": false,
				"bpm": 120,
				"changeBPM": false,
				"mustHitSection": true
			},
			{
				"typeOfSection": 0,
				"sectionNotes": [
					[
						76000,
						1,
						0
					],
					[
						76250,
						0,
						0
					],
					[
						76375,
						2,
						0
					],
					[
						76500,
						3,
						0
					],
					[
						76750,
						2,
						0
					],
					[
						77000,
						1,
						0
					],
					[
						77500,
						3,
						0
					],
					[
						77750,
						2,
						0
					]
				],
				"lengthInSteps": 16,
				"altAnim": false,
				"bpm": 120,
				"changeBPM": false,
				"mustHitSection": true
			},
			{
				"typeOfSection": 0,
				"sectionNotes": [
					[
						78000,
						1,
						0
					],
					[
						78250,
						1,
						0
					],
					[
						78375,
						0,
						0
					],
					[
						78500,
						1,
						0
					],
					[
						78750,
						3,
						0
					],
					[
						78875,
						1,
						0
					]
				],
				"lengthInSteps": 16,
				"altAnim": false,
				"bpm": 120,
				"changeBPM": false,
				"mustHitSection": true
			},
			{
				"typeOfSection": 0,
				"sectionNotes": [
					[
						80000,
						1,
						0
					],
					[
						80375,
						2,
						0
					],
					[
						80750,
						2,
						0
					],
					[
						81000,
						1,
						0
					],
					[
						81375,
						2,
						0
					],
					[
						81750,
						2,
						0
					],
					[
						81625,
						3,
						0
					],
					[
						80000,
						-1,
						"Set Camera Zoom",
						"1.5",
						"2"
					]
				],
				"lengthInSteps": 16,
				"altAnim": false,
				"bpm": 120,
				"changeBPM": false,
				"mustHitSection": false
			},
			{
				"typeOfSection": 0,
				"sectionNotes": [
					[
						82000,
						1,
						0
					],
					[
						82125,
						0,
						0
					],
					[
						82375,
						2,
						0
					],
					[
						82750,
						2,
						0
					],
					[
						83500,
						2,
						0
					],
					[
						83750,
						2,
						0
					],
					[
						83000,
						1,
						0
					],
					[
						83250,
						3,
						0
					]
				],
				"lengthInSteps": 16,
				"altAnim": false,
				"bpm": 120,
				"changeBPM": false,
				"mustHitSection": false
			},
			{
				"typeOfSection": 0,
				"sectionNotes": [
					[
						84000,
						1,
						0
					],
					[
						84375,
						2,
						0
					],
					[
						84750,
						2,
						0
					],
					[
						85000,
						1,
						0
					],
					[
						85375,
						2,
						0
					],
					[
						85750,
						2,
						0
					],
					[
						85625,
						3,
						0
					]
				],
				"lengthInSteps": 16,
				"altAnim": false,
				"bpm": 120,
				"changeBPM": false,
				"mustHitSection": true
			},
			{
				"typeOfSection": 0,
				"sectionNotes": [
					[
						86000,
						1,
						0
					],
					[
						86125,
						0,
						0
					],
					[
						86375,
						2,
						0
					],
					[
						86750,
						2,
						0
					],
					[
						87500,
						2,
						0
					],
					[
						87750,
						2,
						0
					],
					[
						87000,
						1,
						0
					],
					[
						87250,
						3,
						0
					]
				],
				"lengthInSteps": 16,
				"altAnim": false,
				"bpm": 120,
				"changeBPM": false,
				"mustHitSection": true
			},
			{
				"typeOfSection": 0,
				"sectionNotes": [
					[
						88000,
						1,
						0
					],
					[
						88125,
						0,
						0
					],
					[
						88375,
						2,
						0
					],
					[
						88750,
						2,
						0
					],
					[
						89500,
						2,
						0
					],
					[
						89750,
						2,
						0
					],
					[
						89000,
						1,
						0
					],
					[
						89250,
						3,
						0
					]
				],
				"lengthInSteps": 16,
				"altAnim": false,
				"bpm": 120,
				"changeBPM": false,
				"mustHitSection": false
			},
			{
				"typeOfSection": 0,
				"sectionNotes": [
					[
						90000,
						1,
						0
					],
					[
						90125,
						0,
						0
					],
					[
						90375,
						2,
						0
					],
					[
						90750,
						2,
						0
					],
					[
						91500,
						2,
						0
					],
					[
						91000,
						1,
						0
					],
					[
						91125,
						3,
						0
					],
					[
						91250,
						1,
						0
					],
					[
						91375,
						3,
						0
					]
				],
				"lengthInSteps": 16,
				"altAnim": false,
				"bpm": 120,
				"changeBPM": false,
				"mustHitSection": false
			},
			{
				"typeOfSection": 0,
				"sectionNotes": [
					[
						92000,
						1,
						0
					],
					[
						92125,
						0,
						0
					],
					[
						92375,
						2,
						0
					],
					[
						92750,
						2,
						0
					],
					[
						93500,
						2,
						0
					],
					[
						93000,
						3,
						0
					],
					[
						93250,
						1,
						0
					],
					[
						93750,
						2,
						0
					]
				],
				"lengthInSteps": 16,
				"altAnim": false,
				"bpm": 120,
				"changeBPM": false,
				"mustHitSection": true
			},
			{
				"typeOfSection": 0,
				"sectionNotes": [
					[
						94000,
						1,
						0
					],
					[
						94125,
						0,
						0
					],
					[
						94375,
						2,
						0
					],
					[
						94750,
						2,
						0
					],
					[
						95500,
						2,
						0
					],
					[
						95000,
						1,
						0
					],
					[
						95125,
						3,
						0
					],
					[
						95250,
						1,
						0
					]
				],
				"lengthInSteps": 16,
				"altAnim": false,
				"bpm": 120,
				"changeBPM": false,
				"mustHitSection": true
			},
			{
				"typeOfSection": 0,
				"sectionNotes": [
					[
						96000,
						1,
						0
					],
					[
						96250,
						2,
						0
					],
					[
						96500,
						1,
						0
					],
					[
						97000,
						1,
						0
					],
					[
						96000,
						-1,
						"Set Camera Zoom",
						"1",
						"2"
					]
				],
				"lengthInSteps": 16,
				"altAnim": false,
				"bpm": 120,
				"changeBPM": false,
				"mustHitSection": false
			},
			{
				"typeOfSection": 0,
				"sectionNotes": [
					[
						98000,
						1,
						0
					],
					[
						98375,
						2,
						0
					],
					[
						98750,
						1,
						0
					],
					[
						99250,
						1,
						0
					],
					[
						99500,
						1,
						0
					],
					[
						99125,
						0,
						0
					]
				],
				"lengthInSteps": 16,
				"altAnim": false,
				"bpm": 120,
				"changeBPM": false,
				"mustHitSection": false
			},
			{
				"typeOfSection": 0,
				"sectionNotes": [
					[
						100000,
						1,
						0
					],
					[
						100250,
						1,
						0
					],
					[
						100500,
						1,
						0
					],
					[
						100750,
						2,
						0
					],
					[
						100375,
						3,
						0
					],
					[
						101000,
						1,
						0
					]
				],
				"lengthInSteps": 16,
				"altAnim": false,
				"bpm": 120,
				"changeBPM": false,
				"mustHitSection": false
			},
			{
				"typeOfSection": 0,
				"sectionNotes": [
					[
						102000,
						1,
						0
					],
					[
						102250,
						1,
						0
					],
					[
						102500,
						1,
						0
					],
					[
						102375,
						3,
						0
					],
					[
						102750,
						2,
						0
					],
					[
						102875,
						3,
						0
					],
					[
						103125,
						2,
						0
					],
					[
						103250,
						3,
						0
					],
					[
						103375,
						3,
						0
					],
					[
						103500,
						1,
						0
					]
				],
				"lengthInSteps": 16,
				"altAnim": false,
				"bpm": 120,
				"changeBPM": false,
				"mustHitSection": false
			},
			{
				"typeOfSection": 0,
				"sectionNotes": [
					[
						104000,
						1,
						0
					],
					[
						104250,
						2,
						0
					],
					[
						104500,
						1,
						0
					],
					[
						105000,
						1,
						0
					]
				],
				"lengthInSteps": 16,
				"altAnim": false,
				"bpm": 120,
				"changeBPM": false,
				"mustHitSection": true
			},
			{
				"typeOfSection": 0,
				"sectionNotes": [
					[
						106000,
						1,
						0
					],
					[
						106375,
						2,
						0
					],
					[
						106750,
						1,
						0
					],
					[
						107250,
						1,
						0
					],
					[
						107500,
						1,
						0
					],
					[
						107125,
						0,
						0
					]
				],
				"lengthInSteps": 16,
				"altAnim": false,
				"bpm": 120,
				"changeBPM": false,
				"mustHitSection": true
			},
			{
				"typeOfSection": 0,
				"sectionNotes": [
					[
						108000,
						1,
						0
					],
					[
						108250,
						1,
						0
					],
					[
						108500,
						1,
						0
					],
					[
						108750,
						2,
						0
					],
					[
						108375,
						3,
						0
					],
					[
						109000,
						1,
						0
					]
				],
				"lengthInSteps": 16,
				"altAnim": false,
				"bpm": 120,
				"changeBPM": false,
				"mustHitSection": true
			},
			{
				"typeOfSection": 0,
				"sectionNotes": [
					[
						110000,
						1,
						0
					],
					[
						110250,
						1,
						0
					],
					[
						110500,
						1,
						0
					],
					[
						110375,
						3,
						0
					],
					[
						110750,
						2,
						0
					],
					[
						110875,
						3,
						0
					],
					[
						111125,
						2,
						0
					],
					[
						111250,
						3,
						0
					],
					[
						111375,
						2,
						0
					],
					[
						111500,
						0,
						0
					]
				],
				"lengthInSteps": 16,
				"altAnim": false,
				"bpm": 120,
				"changeBPM": false,
				"mustHitSection": true
			},
			{
				"typeOfSection": 0,
				"sectionNotes": [
					[
						112000,
						1,
						0
					],
					[
						112000,
						-1,
						"Default Camera Zoom",
						"0.75",
						""
					],
					[
						112025,
						-1,
						"Set Camera Zoom",
						"0.8",
						"2"
					]
				],
				"lengthInSteps": 16,
				"altAnim": false,
				"bpm": 120,
				"changeBPM": false,
				"mustHitSection": false
			},
			{
				"typeOfSection": 0,
				"sectionNotes": [],
				"lengthInSteps": 16,
				"altAnim": false,
				"bpm": 120,
				"changeBPM": false,
				"mustHitSection": false
			},
			{
				"typeOfSection": 0,
				"sectionNotes": [
					[
						116000,
						2,
						0
					],
					[
						116125,
						3,
						0
					],
					[
						116250,
						1,
						0
					],
					[
						116375,
						3,
						0
					],
					[
						116500,
						1,
						0
					],
					[
						116625,
						3,
						0
					],
					[
						116750,
						2,
						0
					],
					[
						116875,
						0,
						0
					],
					[
						117000,
						3,
						0
					],
					[
						117125,
						0,
						0
					],
					[
						117250,
						1,
						0
					],
					[
						117375,
						3,
						0
					],
					[
						117500,
						1,
						0
					],
					[
						117625,
						3,
						0
					],
					[
						117750,
						2,
						0
					],
					[
						117875,
						0,
						0
					]
				],
				"lengthInSteps": 16,
				"altAnim": false,
				"bpm": 120,
				"changeBPM": false,
				"mustHitSection": true
			},
			{
				"typeOfSection": 0,
				"sectionNotes": [
					[
						118000,
						2,
						0
					],
					[
						118125,
						3,
						0
					],
					[
						118250,
						1,
						0
					],
					[
						118375,
						3,
						0
					],
					[
						118500,
						1,
						0
					],
					[
						118625,
						3,
						0
					],
					[
						118750,
						2,
						0
					],
					[
						118875,
						0,
						0
					],
					[
						119000,
						3,
						0
					],
					[
						119125,
						0,
						0
					],
					[
						119250,
						1,
						0
					],
					[
						119375,
						3,
						0
					],
					[
						119500,
						1,
						0
					],
					[
						119625,
						3,
						0
					],
					[
						119750,
						2,
						0
					],
					[
						119875,
						0,
						0
					]
				],
				"lengthInSteps": 16,
				"altAnim": false,
				"bpm": 120,
				"changeBPM": false,
				"mustHitSection": true
			},
			{
				"typeOfSection": 0,
				"sectionNotes": [
					[
						120000,
						2,
						0
					],
					[
						120125,
						3,
						0
					],
					[
						120250,
						1,
						0
					],
					[
						120375,
						3,
						0
					],
					[
						120500,
						1,
						0
					],
					[
						120625,
						3,
						0
					],
					[
						120750,
						2,
						0
					],
					[
						120875,
						0,
						0
					],
					[
						121000,
						3,
						0
					],
					[
						121125,
						0,
						0
					],
					[
						121250,
						1,
						0
					],
					[
						121375,
						3,
						0
					],
					[
						121500,
						1,
						0
					],
					[
						121625,
						3,
						0
					],
					[
						121750,
						2,
						0
					],
					[
						121875,
						0,
						0
					]
				],
				"lengthInSteps": 16,
				"altAnim": false,
				"bpm": 120,
				"changeBPM": false,
				"mustHitSection": false
			},
			{
				"typeOfSection": 0,
				"sectionNotes": [
					[
						122000,
						2,
						0
					],
					[
						122125,
						3,
						0
					],
					[
						122250,
						1,
						0
					],
					[
						122375,
						3,
						0
					],
					[
						122500,
						1,
						0
					],
					[
						122625,
						3,
						0
					],
					[
						122750,
						2,
						0
					],
					[
						122875,
						0,
						0
					],
					[
						123000,
						3,
						0
					],
					[
						123125,
						0,
						0
					],
					[
						123250,
						1,
						0
					],
					[
						123375,
						3,
						0
					],
					[
						123500,
						1,
						0
					],
					[
						123625,
						3,
						0
					],
					[
						123750,
						2,
						0
					],
					[
						123875,
						0,
						0
					]
				],
				"lengthInSteps": 16,
				"altAnim": false,
				"bpm": 120,
				"changeBPM": false,
				"mustHitSection": false
			},
			{
				"typeOfSection": 0,
				"sectionNotes": [
					[
						124000,
						2,
						0
					],
					[
						124125,
						3,
						0
					],
					[
						124250,
						1,
						0
					],
					[
						124375,
						3,
						0
					],
					[
						124500,
						1,
						0
					],
					[
						124625,
						3,
						0
					],
					[
						124750,
						2,
						0
					],
					[
						124875,
						0,
						0
					],
					[
						125000,
						3,
						0
					],
					[
						125125,
						0,
						0
					],
					[
						125250,
						1,
						0
					],
					[
						125375,
						3,
						0
					],
					[
						125500,
						1,
						0
					],
					[
						125625,
						3,
						0
					],
					[
						125750,
						2,
						0
					],
					[
						125875,
						0,
						0
					]
				],
				"lengthInSteps": 16,
				"altAnim": false,
				"bpm": 120,
				"changeBPM": false,
				"mustHitSection": true
			},
			{
				"typeOfSection": 0,
				"sectionNotes": [
					[
						126000,
						2,
						0
					],
					[
						126125,
						3,
						0
					],
					[
						126250,
						1,
						0
					],
					[
						126375,
						3,
						0
					],
					[
						126500,
						1,
						0
					],
					[
						126625,
						3,
						0
					],
					[
						126750,
						2,
						0
					],
					[
						126875,
						0,
						0
					],
					[
						127000,
						3,
						0
					],
					[
						127125,
						0,
						0
					],
					[
						127250,
						1,
						0
					],
					[
						127375,
						3,
						0
					],
					[
						127500,
						1,
						0
					],
					[
						127625,
						3,
						0
					],
					[
						127750,
						2,
						0
					],
					[
						127875,
						0,
						0
					]
				],
				"lengthInSteps": 16,
				"altAnim": false,
				"bpm": 120,
				"changeBPM": false,
				"mustHitSection": true
			},
			{
				"typeOfSection": 0,
				"sectionNotes": [
					[
						129946.875,
						0,
						0
					],
					[
						129875,
						1,
						0
					],
					[
						129815.625,
						2,
						0
					],
					[
						129750,
						1,
						0
					],
					[
						129690.625,
						3,
						0
					],
					[
						129625,
						2,
						0
					],
					[
						129575,
						0,
						0
					],
					[
						129500,
						1,
						0
					],
					[
						129443.75,
						2,
						0
					],
					[
						129375,
						3,
						0
					],
					[
						129318.75,
						2,
						0
					],
					[
						129250,
						1,
						0
					],
					[
						129221.875,
						0,
						0
					],
					[
						129190.625,
						3,
						0
					],
					[
						129121.875,
						2,
						0
					],
					[
						129053.125,
						1,
						0
					],
					[
						128875,
						0,
						0
					],
					[
						129000,
						3,
						0
					],
					[
						128940.625,
						2,
						0
					],
					[
						128821.875,
						1,
						0
					],
					[
						128750,
						2,
						0
					],
					[
						128681.25,
						3,
						0
					],
					[
						128625,
						2,
						0
					],
					[
						128562.5,
						1,
						0
					],
					[
						128500,
						0,
						0
					],
					[
						128690.625,
						0,
						0
					],
					[
						128450,
						1,
						0
					],
					[
						128428.125,
						3,
						0
					],
					[
						128375,
						2,
						0
					],
					[
						128318.75,
						1,
						0
					],
					[
						128250,
						0,
						0
					],
					[
						128196.875,
						3,
						0
					],
					[
						128321.875,
						3,
						0
					],
					[
						128190.625,
						2,
						0
					],
					[
						128125,
						0,
						0
					],
					[
						128062.5,
						3,
						0
					],
					[
						128031.25,
						1,
						0
					],
					[
						128000,
						-1,
						"Default Camera Zoom",
						"2",
						"0.5"
					],
					[
						128025,
						-1,
						"Default CamHUD Zoom",
						"1.25",
						"20"
					]
				],
				"lengthInSteps": 16,
				"altAnim": false,
				"bpm": 120,
				"changeBPM": false,
				"mustHitSection": false
			},
			{
				"typeOfSection": 0,
				"sectionNotes": [
					[
						131946.875,
						0,
						0
					],
					[
						131875,
						1,
						0
					],
					[
						131815.625,
						2,
						0
					],
					[
						131750,
						1,
						0
					],
					[
						131690.625,
						3,
						0
					],
					[
						131625,
						2,
						0
					],
					[
						131575,
						0,
						0
					],
					[
						131500,
						1,
						0
					],
					[
						131443.75,
						2,
						0
					],
					[
						131375,
						3,
						0
					],
					[
						131318.75,
						2,
						0
					],
					[
						131250,
						1,
						0
					],
					[
						131221.875,
						0,
						0
					],
					[
						131190.625,
						3,
						0
					],
					[
						131121.875,
						2,
						0
					],
					[
						131053.125,
						1,
						0
					],
					[
						130875,
						0,
						0
					],
					[
						131000,
						3,
						0
					],
					[
						130940.625,
						2,
						0
					],
					[
						130821.875,
						1,
						0
					],
					[
						130750,
						2,
						0
					],
					[
						130681.25,
						3,
						0
					],
					[
						130625,
						2,
						0
					],
					[
						130562.5,
						1,
						0
					],
					[
						130500,
						0,
						0
					],
					[
						130690.625,
						0,
						0
					],
					[
						130450,
						1,
						0
					],
					[
						130428.125,
						3,
						0
					],
					[
						130375,
						2,
						0
					],
					[
						130318.75,
						1,
						0
					],
					[
						130250,
						0,
						0
					],
					[
						130196.875,
						3,
						0
					],
					[
						130321.875,
						3,
						0
					],
					[
						130190.625,
						2,
						0
					],
					[
						130125,
						0,
						0
					],
					[
						130062.5,
						3,
						0
					],
					[
						130031.25,
						1,
						0
					],
					[
						130000,
						-1,
						"Default Camera Zoom",
						"3",
						"0.5"
					],
					[
						130025,
						-1,
						"Default CamHUD Zoom",
						"1.5",
						"20"
					]
				],
				"lengthInSteps": 16,
				"altAnim": false,
				"bpm": 120,
				"changeBPM": false,
				"mustHitSection": false
			},
			{
				"typeOfSection": 0,
				"sectionNotes": [
					[
						133946.875,
						0,
						0
					],
					[
						133875,
						1,
						0
					],
					[
						133815.625,
						2,
						0
					],
					[
						133750,
						1,
						0
					],
					[
						133690.625,
						3,
						0
					],
					[
						133625,
						2,
						0
					],
					[
						133575,
						0,
						0
					],
					[
						133500,
						1,
						0
					],
					[
						133443.75,
						2,
						0
					],
					[
						133375,
						3,
						0
					],
					[
						133318.75,
						2,
						0
					],
					[
						133250,
						1,
						0
					],
					[
						133221.875,
						0,
						0
					],
					[
						133190.625,
						3,
						0
					],
					[
						133121.875,
						2,
						0
					],
					[
						133053.125,
						1,
						0
					],
					[
						132875,
						0,
						0
					],
					[
						133000,
						3,
						0
					],
					[
						132940.625,
						2,
						0
					],
					[
						132821.875,
						1,
						0
					],
					[
						132750,
						2,
						0
					],
					[
						132681.25,
						3,
						0
					],
					[
						132625,
						2,
						0
					],
					[
						132562.5,
						1,
						0
					],
					[
						132500,
						0,
						0
					],
					[
						132690.625,
						0,
						0
					],
					[
						132450,
						1,
						0
					],
					[
						132428.125,
						3,
						0
					],
					[
						132375,
						2,
						0
					],
					[
						132318.75,
						1,
						0
					],
					[
						132250,
						0,
						0
					],
					[
						132196.875,
						3,
						0
					],
					[
						132321.875,
						3,
						0
					],
					[
						132190.625,
						2,
						0
					],
					[
						132125,
						0,
						0
					],
					[
						132062.5,
						3,
						0
					],
					[
						132031.25,
						1,
						0
					],
					[
						132000,
						-1,
						"Default Camera Zoom",
						"4",
						"0.5"
					],
					[
						132025,
						-1,
						"Default CamHUD Zoom",
						"1.75",
						"20"
					]
				],
				"lengthInSteps": 16,
				"altAnim": false,
				"bpm": 120,
				"changeBPM": false,
				"mustHitSection": false
			},
			{
				"typeOfSection": 0,
				"sectionNotes": [
					[
						134000,
						3,
						0
					],
					[
						134250,
						2,
						0
					],
					[
						134500,
						1,
						0
					],
					[
						134750,
						0,
						0
					],
					[
						135000,
						1,
						0
					],
					[
						135250,
						2,
						0
					],
					[
						135500,
						3,
						0
					],
					[
						135750,
						2,
						0
					],
					[
						134025,
						-1,
						"Default CamHUD Zoom",
						"1",
						""
					],
					[
						134000,
						-1,
						"Default Camera Zoom",
						"1",
						"8"
					]
				],
				"lengthInSteps": 16,
				"altAnim": false,
				"bpm": 120,
				"changeBPM": false,
				"mustHitSection": false
			},
			{
				"typeOfSection": 0,
				"sectionNotes": [
					[
						136000,
						1,
						0
					],
					[
						136250,
						0,
						0
					],
					[
						136500,
						1,
						0
					],
					[
						136750,
						2,
						0
					],
					[
						137000,
						3,
						0
					],
					[
						137250,
						2,
						0
					],
					[
						137500,
						1,
						0
					],
					[
						137750,
						0,
						0
					]
				],
				"lengthInSteps": 16,
				"altAnim": false,
				"bpm": 120,
				"changeBPM": false,
				"mustHitSection": false
			},
			{
				"typeOfSection": 0,
				"sectionNotes": [
					[
						138000,
						1,
						0
					],
					[
						138250,
						1,
						0
					],
					[
						138625,
						1,
						0
					],
					[
						139250,
						1,
						0
					],
					[
						139875,
						1,
						0
					]
				],
				"lengthInSteps": 16,
				"altAnim": false,
				"bpm": 120,
				"changeBPM": false,
				"mustHitSection": false
			},
			{
				"typeOfSection": 0,
				"sectionNotes": [
					[
						141125,
						1,
						0
					],
					[
						140250,
						1,
						0
					]
				],
				"lengthInSteps": 16,
				"altAnim": false,
				"bpm": 120,
				"changeBPM": false,
				"mustHitSection": false
			},
			{
				"typeOfSection": 0,
				"sectionNotes": [
					[
						142125,
						1,
						0
					]
				],
				"lengthInSteps": 16,
				"altAnim": false,
				"bpm": 120,
				"changeBPM": false,
				"mustHitSection": false
			},
			{
				"lengthInSteps": 16,
				"typeOfSection": 0,
				"sectionNotes": [],
				"altAnim": false,
				"bpm": 120,
				"changeBPM": false,
				"mustHitSection": true
			},
			{
				"lengthInSteps": 16,
				"typeOfSection": 0,
				"sectionNotes": [],
				"altAnim": false,
				"bpm": 120,
				"changeBPM": false,
				"mustHitSection": true
			},
			{
				"lengthInSteps": 16,
				"typeOfSection": 0,
				"sectionNotes": [],
				"altAnim": false,
				"bpm": 120,
				"changeBPM": false,
				"mustHitSection": true
			},
			{
				"sectionNotes": [],
				"typeOfSection": 0,
				"lengthInSteps": 16,
				"altAnim": false,
				"mustHitSection": true,
				"changeBPM": false,
				"bpm": 120
			},
			{
				"lengthInSteps": 16,
				"typeOfSection": 0,
				"sectionNotes": [],
				"altAnim": false,
				"bpm": 120,
				"changeBPM": false,
				"mustHitSection": true
			},
			{
				"sectionNotes": [],
				"typeOfSection": 0,
				"lengthInSteps": 16,
				"altAnim": false,
				"mustHitSection": true,
				"changeBPM": false,
				"bpm": 120
			},
			{
				"lengthInSteps": 16,
				"altAnim": false,
				"typeOfSection": 0,
				"sectionNotes": [],
				"bpm": 120,
				"changeBPM": false,
				"mustHitSection": true
			},
			{
				"lengthInSteps": 16,
				"bpm": 120,
				"changeBPM": false,
				"mustHitSection": true,
				"sectionNotes": [],
				"typeOfSection": 0,
				"altAnim": false
			}
		],
		"player3": "gf",
		"mania": 3,
		"song": "Sizzled",
		"stage": "rematch",
		"validScore": true,
		"sections": 0,
		"needsVoices": true,
		"speed": 2.3,
		"bpm": 120,
		"timebarColor": [
			"0xFF915D0F",
			""
		],
		"noBotplay": false,
		"noPractice": false,
		"forceMiddlescroll": false,
		"forceGhostingOff": false,
		"hideGF": false,
		"disableChartEditor": false,
		"soundPrefix": "",
		"fontColor": ""
	}
}